elicznik/__init__.py
elicznik/__main__.py
elicznik/elicznik.py
elicznik/session.py
elicznik-2.2.1.dist-info/LICENSE
elicznik-2.2.1.dist-info/METADATA
elicznik-2.2.1.dist-info/WHEEL
elicznik-2.2.1.dist-info/entry_points.txt
elicznik-2.2.1.dist-info/top_level.txt
elicznik-2.2.1.dist-info/RECORD
