Metadata-Version: 2.1
Name: elicznik
Version: 2.2.1
Summary: Tauron eLicznik scrapper
Home-page: https://github.com/mlesniew/elicznik
Author: Michał Leśniewski
Author-email: mlesniew@gmail.com
Keywords: elicznik,tauron,scrapper
Classifier: Development Status :: 4 - Beta
Classifier: Environment :: Console
Classifier: Intended Audience :: Developers
Classifier: License :: OSI Approved :: MIT License
Classifier: Programming Language :: Python :: 3 :: Only
Classifier: Programming Language :: Python :: 3
Classifier: Topic :: Home Automation
Classifier: Topic :: Internet
Classifier: Topic :: Utilities
Requires-Python: >=3.6, <4
License-File: LICENSE
Requires-Dist: requests
Requires-Dist: tabulate
